fixa/__init__.py
fixa/_version.py
fixa/agent.py
fixa/bot.py
fixa/evaluation.py
fixa/scenario.py
fixa/test.py
fixa/utils.py
fixa/evaluators/__init__.py
fixa/evaluators/cloud.py
fixa/evaluators/evaluator.py
fixa/evaluators/local.py
fixa/telemetry/__init__.py
fixa/telemetry/service.py
fixa/telemetry/views.py
fixa/test_runner/server.py
fixa/test_runner/service.py
fixa/test_runner/views.py
fixa_dev-0.0.4.dist-info/LICENSE
fixa_dev-0.0.4.dist-info/METADATA
fixa_dev-0.0.4.dist-info/WHEEL
fixa_dev-0.0.4.dist-info/top_level.txt
fixa_dev-0.0.4.dist-info/RECORD
