Metadata-Version: 2.2
Name: fixa-dev
Version: 0.0.4
Summary: A tool for testing and evaluating AI voice agents
License: BSD 2-Clause License
Project-URL: Homepage, https://fixa.dev
Project-URL: Repository, https://github.com/fixadev/fixa
Project-URL: Issues, https://github.com/fixadev/fixa/issues
Classifier: Programming Language :: Python :: 3
Classifier: Intended Audience :: Developers
Classifier: Topic :: Scientific/Engineering :: Artificial Intelligence
Classifier: Topic :: Software Development :: Testing
Classifier: Topic :: Software Development :: Testing :: Unit
Classifier: License :: OSI Approved :: BSD License
Requires-Python: >=3.10
License-File: LICENSE
Requires-Dist: pipecat-ai[cartesia,deepgram,openai,silero]==0.0.53
Requires-Dist: posthog==3.11.0
Requires-Dist: fastapi~=0.115.6
Requires-Dist: uvicorn~=0.34.0
Requires-Dist: python-dotenv~=1.0.1
Requires-Dist: pydantic~=2.10.4
Requires-Dist: twilio~=9.4.3
Requires-Dist: ngrok~=1.4.0
Requires-Dist: python-multipart~=0.0.20
